odoo10_addon_base_multi_image-10.0.1.0.0-py2.7-nspkg.pth
odoo10_addon_base_multi_image-10.0.1.0.0.dist-info/top_level.txt
odoo10_addon_base_multi_image-10.0.1.0.0.dist-info/WHEEL
odoo10_addon_base_multi_image-10.0.1.0.0.dist-info/RECORD
odoo10_addon_base_multi_image-10.0.1.0.0.dist-info/metadata.json
odoo10_addon_base_multi_image-10.0.1.0.0.dist-info/DESCRIPTION.rst
odoo10_addon_base_multi_image-10.0.1.0.0.dist-info/METADATA
odoo10_addon_base_multi_image-10.0.1.0.0.dist-info/namespace_packages.txt
odoo/addons/base_multi_image/__manifest__.py
odoo/addons/base_multi_image/hooks.py
odoo/addons/base_multi_image/__init__.py
odoo/addons/base_multi_image/README.rst
odoo/addons/base_multi_image/security/ir.model.access.csv
odoo/addons/base_multi_image/models/__init__.py
odoo/addons/base_multi_image/models/image.py
odoo/addons/base_multi_image/models/owner.py
odoo/addons/base_multi_image/i18n/zh_CN.po
odoo/addons/base_multi_image/i18n/ru.po
odoo/addons/base_multi_image/i18n/pt.po
odoo/addons/base_multi_image/i18n/it.po
odoo/addons/base_multi_image/i18n/es.po
odoo/addons/base_multi_image/i18n/tr.po
odoo/addons/base_multi_image/i18n/hr.po
odoo/addons/base_multi_image/i18n/bg.po
odoo/addons/base_multi_image/i18n/fr_CA.po
odoo/addons/base_multi_image/i18n/gl.po
odoo/addons/base_multi_image/i18n/ca.po
odoo/addons/base_multi_image/i18n/sl.po
odoo/addons/base_multi_image/i18n/es_ES.po
odoo/addons/base_multi_image/i18n/pt_PT.po
odoo/addons/base_multi_image/i18n/nl.po
odoo/addons/base_multi_image/i18n/am.po
odoo/addons/base_multi_image/i18n/de.po
odoo/addons/base_multi_image/i18n/fr.po
odoo/addons/base_multi_image/i18n/pt_BR.po
odoo/addons/base_multi_image/i18n/el_GR.po
odoo/addons/base_multi_image/i18n/sv.po
odoo/addons/base_multi_image/i18n/fi.po
odoo/addons/base_multi_image/i18n/hr_HR.po
odoo/addons/base_multi_image/views/image_view.xml
odoo/addons/base_multi_image/images/form.png
odoo/addons/base_multi_image/images/kanban.png
odoo/addons/base_multi_image/static/description/icon.svg
odoo/addons/base_multi_image/static/description/icon.png
